{
  "todolist": [
    {
      "id": 1,
      "date": "2023-2-1",
      "title": "111",
      "content": "111"
    },
    {
      "id": 2,
      "date": "2023-2-1",
      "title": "222",
      "content": "222"
    },
    {
      "id": 3,
      "date": "2023-2-1",
      "title": "333",
      "content": "333"
    },
    {
      "id": 4,
      "date": "2023-2-1",
      "title": "333",
      "content": "333"
    },
    {
      "id": 5,
      "date": "2023-2-1",
      "title": "333",
      "content": "333"
    },
    {
      "id": 6,
      "date": "2023-2-1",
      "title": "4444",
      "content": "4444"
    },
    {
      "id": 7,
      "date": "2023-2-1",
      "title": "346346",
      "content": "346346"
    },
    {
      "id": 8,
      "date": "2023-2-2",
      "title": "23423",
      "content": "234234"
    },
    {
      "id": 9,
      "date": "2023-2-1",
      "title": "111111",
      "content": "111111"
    },
    {
      "id": 10,
      "date": "2023-2-1",
      "title": "555",
      "content": "555"
    },
    {
      "id": 11,
      "date": "2023-2-4",
      "title": "5522",
      "content": "2222"
    },
    {
      "id": 12,
      "date": "2023-2-1",
      "title": "124124",
      "content": "124124"
    },
    {
      "id": 13,
      "date": "2023-2-2",
      "title": "123123",
      "content": "123123"
    },
    {
      "id": 14,
      "date": "2023-2-1",
      "title": "fgsdfgsdfg651",
      "content": "457457"
    },
    {
      "id": 15,
      "date": "2023-2-1",
      "title": "6636364364346",
      "content": "34634634646"
    }
  ]
}